MANIFEST.in
README.rst
setup.py
aliyunsdkecs/__init__.py
aliyunsdkecs/request/__init__.py
aliyunsdkecs/request/v20140526/ActivateRouterInterfaceRequest.py
aliyunsdkecs/request/v20140526/AddBandwidthPackageIpsRequest.py
aliyunsdkecs/request/v20140526/AddIpRangeRequest.py
aliyunsdkecs/request/v20140526/AddTagsRequest.py
aliyunsdkecs/request/v20140526/AllocateEipAddressRequest.py
aliyunsdkecs/request/v20140526/AllocatePublicIpAddressRequest.py
aliyunsdkecs/request/v20140526/ApplyAutoSnapshotPolicyRequest.py
aliyunsdkecs/request/v20140526/AssignPrivateIpAddressesRequest.py
aliyunsdkecs/request/v20140526/AssociateEipAddressRequest.py
aliyunsdkecs/request/v20140526/AssociateHaVipRequest.py
aliyunsdkecs/request/v20140526/AttachClassicLinkVpcRequest.py
aliyunsdkecs/request/v20140526/AttachDiskRequest.py
aliyunsdkecs/request/v20140526/AttachInstanceRamRoleRequest.py
aliyunsdkecs/request/v20140526/AttachKeyPairRequest.py
aliyunsdkecs/request/v20140526/AttachNetworkInterfaceRequest.py
aliyunsdkecs/request/v20140526/AuthorizeSecurityGroupEgressRequest.py
aliyunsdkecs/request/v20140526/AuthorizeSecurityGroupRequest.py
aliyunsdkecs/request/v20140526/BindIpRangeRequest.py
aliyunsdkecs/request/v20140526/CancelAgreementRequest.py
aliyunsdkecs/request/v20140526/CancelAutoSnapshotPolicyRequest.py
aliyunsdkecs/request/v20140526/CancelCopyImageRequest.py
aliyunsdkecs/request/v20140526/CancelPhysicalConnectionRequest.py
aliyunsdkecs/request/v20140526/CancelTaskRequest.py
aliyunsdkecs/request/v20140526/CheckAutoSnapshotPolicyRequest.py
aliyunsdkecs/request/v20140526/CheckDiskEnableAutoSnapshotValidationRequest.py
aliyunsdkecs/request/v20140526/ConnectRouterInterfaceRequest.py
aliyunsdkecs/request/v20140526/ConvertNatPublicIpToEipRequest.py
aliyunsdkecs/request/v20140526/CopyImageRequest.py
aliyunsdkecs/request/v20140526/CreateAutoSnapshotPolicyRequest.py
aliyunsdkecs/request/v20140526/CreateCommandRequest.py
aliyunsdkecs/request/v20140526/CreateDeploymentSetRequest.py
dd_aliyun_python_sdk_ecs.egg-info/PKG-INFO
dd_aliyun_python_sdk_ecs.egg-info/SOURCES.txt
dd_aliyun_python_sdk_ecs.egg-info/dependency_links.txt
dd_aliyun_python_sdk_ecs.egg-info/requires.txt
dd_aliyun_python_sdk_ecs.egg-info/top_level.txt